ShellContexts/__init__.py
ShellContexts/base.py
ShellContexts/contexts.py
ShellContexts-1.0.0.dist-info/LICENSE
ShellContexts-1.0.0.dist-info/METADATA
ShellContexts-1.0.0.dist-info/WHEEL
ShellContexts-1.0.0.dist-info/top_level.txt
ShellContexts-1.0.0.dist-info/RECORD
