Metadata-Version: 2.2
Name: ShellContexts
Version: 1.0.0
Summary: A few useful context managers for temporarily changing the environment
License:                     GNU GENERAL PUBLIC LICENSE
Project-URL: Homepage, https://github.com/jb2170/ShellContexts/
License-File: LICENSE
